crystal_projector/__init__.py
crystal_projector/__main__.py
crystal_projector/database.py
crystal_projector/mod.py
crystal_projector/save.py
crystal_projector/texture_pack.py
crystal_projector/version.py
crystal_projector/world.py
crystal_projector-0.1.0.dist-info/LICENSE.md
crystal_projector-0.1.0.dist-info/METADATA
crystal_projector-0.1.0.dist-info/WHEEL
crystal_projector-0.1.0.dist-info/entry_points.txt
crystal_projector-0.1.0.dist-info/top_level.txt
crystal_projector-0.1.0.dist-info/RECORD
