Metadata-Version: 2.1
Name: crystal-projector
Version: 0.1.0
Summary: Manipulate Crystal Project game data.
Home-page: https://github.com/iconmaster5326/CrystalProjector
Author: iconmaster5326
Classifier: Development Status :: 3 - Alpha
Classifier: Intended Audience :: End Users/Desktop
Classifier: Topic :: Games/Entertainment
Classifier: License :: OSI Approved :: MIT License
Classifier: Programming Language :: Python :: 3
Requires-Python: >=3.8, <4
License-File: LICENSE.md
Requires-Dist: Pillow
Provides-Extra: dev
Requires-Dist: pre-commit ; extra == 'dev'
Provides-Extra: test
Requires-Dist: jsonschema ; extra == 'test'
Requires-Dist: pyyaml ; extra == 'test'
